{
	"id": "CU9GMkxwi4Y4tvB",
	"json": "{\"id\":\"CU9GMkxwi4Y4tvB\",\"url\":\"https://www.snipaste.com/favicon.ico\",\"loadedUrl\":\"https://www.snipaste.com/favicon.ico\",\"uniqueKey\":\"https://www.snipaste.com/favicon.ico\",\"method\":\"GET\",\"noRetry\":false,\"retryCount\":0,\"errorMessages\":[],\"headers\":{},\"userData\":{\"__crawlee\":{\"state\":4}},\"handledAt\":\"2023-05-18T13:23:16.116Z\"}",
	"method": "GET",
	"orderNo": null,
	"retryCount": 0,
	"uniqueKey": "https://www.snipaste.com/favicon.ico",
	"url": "https://www.snipaste.com/favicon.ico"
}